orderedsets/__init__.py
orderedsets/py.typed
orderedsets-2025.2.dist-info/METADATA
orderedsets-2025.2.dist-info/WHEEL
orderedsets-2025.2.dist-info/licenses/LICENSE
orderedsets-2025.2.dist-info/RECORD
