Metadata-Version: 2.4
Name: orderedsets
Version: 2025.2
Summary: An implementation of mutable and immutable ordered sets.
Project-URL: Homepage, https://github.com/matthiasdiener/orderedsets/
Project-URL: Documentation, https://matthiasdiener.github.io/orderedsets
Project-URL: Issues, https://github.com/matthiasdiener/orderedsets/issues
Author-email: Matthias Diener <matthias.diener@gmail.com>, Andreas Kloeckner <inform@tiker.net>
License: MIT License
License-File: LICENSE
Classifier: License :: OSI Approved :: MIT License
Classifier: Operating System :: OS Independent
Classifier: Programming Language :: Python :: 3
Classifier: Topic :: Software Development :: Libraries
Requires-Python: >=3.7
Requires-Dist: importlib-metadata; python_version < '3.8'
Requires-Dist: more-itertools
